{
    "dependencies": [
        {
            "assetId": "1aPW5eMfMPeP1615dXiqyN",
            "exportId": "7677f969-a0ad-4480-a2a8-f9a41ec2a5b1",
            "id": "0f7a0bbe-777c-41a5-b979-0b0430f25836",
            "name": "SpectaclesInteractionKit",
            "version": "0.13.0"
        },
        {
            "assetId": "6t4hhnuVFexlUIGORHNqEJ",
            "exportId": "39f12eca-4072-49c0-88b0-6545f88131f6",
            "id": "3531b844-8e67-4633-9afa-7f4233cbd9e2",
            "name": "Remote Service Gateway",
            "version": "0.1.2"
        },
        {
            "assetId": "01nh49tLS3W7scF2JNRBJe",
            "exportId": "3b5eba1c-a4e8-4124-8c07-5f3222a5289a",
            "id": "d0c06990-bb77-41d8-905a-5f74c66c942c",
            "name": "LSTween",
            "version": "1.0.1"
        }
    ]
}